filedialogs/__init__.py
filedialogs/filedialogs.py
filedialogs/py.typed
LICENSE
README.md
windows_filedialogs-0.0.7.dist-info/LICENSE
windows_filedialogs-0.0.7.dist-info/METADATA
windows_filedialogs-0.0.7.dist-info/WHEEL
windows_filedialogs-0.0.7.dist-info/RECORD
