Metadata-Version: 2.1
Name: windows_filedialogs
Version: 0.0.7
Summary: Simple Windows file dialogs.
Home-page: https://mrthearman.github.io/filedialogs
License: MIT
Keywords: file,dialogs,windows,open,save
Author: Matti Lamppu
Author-email: lamppu.matti.akseli@gmail.com
Requires-Python: >=3.8,<4
Classifier: Intended Audience :: Developers
Classifier: License :: OSI Approved :: MIT License
Classifier: Natural Language :: English
Classifier: Operating System :: Microsoft :: Windows
Classifier: Operating System :: Microsoft :: Windows :: Windows 10
Classifier: Operating System :: Microsoft :: Windows :: Windows 11
Classifier: Programming Language :: Python
Classifier: Programming Language :: Python :: 3
Classifier: Programming Language :: Python :: 3.8
Classifier: Programming Language :: Python :: 3.9
Classifier: Programming Language :: Python :: 3.10
Classifier: Programming Language :: Python :: 3.11
Classifier: Programming Language :: Python :: 3 :: Only
Classifier: Programming Language :: Python :: 3.12
Requires-Dist: pywin32 (>=306)
Project-URL: Bug Tracker, https://github.com/MrThearMan/filedialogs/issues
Project-URL: Repository, https://github.com/MrThearMan/filedialogs
